grepjson.py
grepjson-0.2.2.dist-info/METADATA
grepjson-0.2.2.dist-info/WHEEL
grepjson-0.2.2.dist-info/entry_points.txt
grepjson-0.2.2.dist-info/top_level.txt
grepjson-0.2.2.dist-info/RECORD
