Metadata-Version: 2.1
Name: grepjson
Version: 0.2.2
Summary: Interactively inspect or process JSON/JSONL data from pipe.
Home-page: https://github.com/juhayna-zh/grepjson
Author: Juhayna
Author-email: juhayna@foxmail.com
Keywords: json debug cli
Classifier: Programming Language :: Python :: 3
Classifier: License :: OSI Approved :: MIT License
Classifier: Operating System :: OS Independent
